starman/__init__.py
starman/charts.py
starman/cli.py
starman/config.py
starman/loader.py
starman/paths.py
starman/render.py
starman/requester.py
starman/response.py
starman/charts/sample/delete.yaml
starman/charts/sample/get.yaml
starman/charts/sample/manifest.yaml
starman/charts/sample/post.yaml
starman/charts/sample/get/other.yaml
starman/charts/sample/get/users.yaml
starman_cli-1.0.2.dist-info/METADATA
starman_cli-1.0.2.dist-info/WHEEL
starman_cli-1.0.2.dist-info/entry_points.txt
starman_cli-1.0.2.dist-info/licenses/LICENSE
starman_cli-1.0.2.dist-info/RECORD
