Metadata-Version: 2.4
Name: starman-cli
Version: 1.0.2
Summary: A CLI tool for executing customizable API requests
Project-URL: Homepage, https://github.com/cjgala/starman-cli
Project-URL: Issues, https://github.com/cjgala/starman-cli/issues
Author: Charles Gala
License-File: LICENSE
Classifier: License :: OSI Approved :: MIT License
Classifier: Operating System :: OS Independent
Classifier: Programming Language :: Python :: 3
Requires-Python: >=3.9
